{
  "UI": {
    "$ui-background": {
      "value": "#f7f9fa",
      "type": "color"
    },
    "$ui-04": {
      "value": "#96afc4",
      "type": "color"
    },
    "$ui-05": {
      "value": "#829db4",
      "type": "color"
    },
    "$ui-06": {
      "value": "#567a98",
      "type": "color"
    },
    "$ui-overlay-01": {
      "value": "#8295a5b8",
      "type": "color"
    },
    "$ui-overlay-02": {
      "value": "#000000bf",
      "type": "color"
    },
    "$ui-overlay-03": {
      "value": "#00000073",
      "type": "color"
    },
    "$ui-supportive-01": {
      "value": "#ed3e3e",
      "type": "color"
    },
    "$ui-supportive-02": {
      "value": "#e4f5ef",
      "type": "color"
    },
    "$ui-supportive-03": {
      "value": "#008cff",
      "type": "color"
    },
    "$ui-supportive-04": {
      "value": "#0077d9",
      "type": "color"
    },
    "$ui-supportive-05": {
      "value": "#172c55",
      "type": "color"
    },
    "$ui-01": {
      "$ui-01": {
        "value": "#ffffff",
        "type": "color",
        "description": "white"
      },
      "$hover-ui-01": {
        "1": {
          "value": "#f7f9fa",
          "type": "color"
        },
        "value": "#e8eff3",
        "type": "color"
      },
      "$active-ui-01": {
        "1": {
          "value": "#f3f7f9",
          "type": "color"
        },
        "value": "#172c55",
        "type": "color"
      }
    },
    "$ui-02": {
      "$ui-02": {
        "value": "#f7f9fa",
        "type": "color"
      },
      "$hover-ui-02": {
        "value": "#e8eff3",
        "type": "color"
      },
      "$active-ui-02": {
        "value": "#c3d1d9",
        "type": "color"
      }
    },
    "$ui-03": {
      "$ui-03": {
        "value": "#e8eff3",
        "type": "color"
      },
      "$hover-ui-03": {
        "value": "#dde8ed",
        "type": "color"
      },
      "$active-ui-03": {
        "1": {
          "value": "#c3d1d9",
          "type": "color"
        },
        "value": "#ffffff",
        "type": "color"
      }
    },
    "$tag-01": {
      "$tag-01": {
        "value": "#ff008a",
        "type": "color"
      },
      "$tag-02": {
        "value": "#6100ff",
        "type": "color"
      },
      "$tag-03": {
        "value": "#ffae03",
        "type": "color"
      },
      "$tag-04": {
        "value": "#ed3e3e",
        "type": "color"
      },
      "$tag-05": {
        "value": "#35e918",
        "type": "color"
      },
      "$tag-06": {
        "value": "#0047ff",
        "type": "color"
      }
    }
  },
  "Interactional": {
    "$disabled-interactional-01": {
      "value": "#e1e1e1",
      "type": "color"
    },
    "$disabled-interactional-02": {
      "value": "#ebeaea",
      "type": "color"
    },
    "$interactional-supporitve-01": {
      "value": "#00a958",
      "type": "color"
    },
    "$interactional-primary-01": {
      "$interactional-primary-01": {
        "value": "#008cff",
        "type": "color"
      },
      "$hover-interactional-primary-01": {
        "value": "#007ee6",
        "type": "color"
      },
      "$active-interactional-primary-01": {
        "value": "#0077d9",
        "type": "color"
      }
    },
    "$interactional-primary-02": {
      "$interactional-primary-02": {
        "value": "#172c55",
        "type": "color"
      },
      "$hover-interactional-primary-02": {
        "value": "#374156",
        "type": "color"
      },
      "$active-interactional-primary-02": {
        "value": "#687387",
        "type": "color"
      }
    },
    "$interactional-secondary-01": {
      "$interactional-secondary-01": {
        "value": "#829db4",
        "type": "color"
      },
      "$hover-interactional-secondary-01": {
        "value": "#758da2",
        "type": "color"
      },
      "$active-interactional-secondary-01": {
        "value": "#6f8599",
        "type": "color"
      }
    },
    "$interactional-secondary-02": {
      "$interactional-secondary-02": {
        "value": "#ed3e3e",
        "type": "color"
      },
      "$hover-interactional-secondary-02": {
        "value": "#cb2d3b",
        "type": "color"
      },
      "$active-interactional-secondary-02": {
        "value": "#cb2d3b",
        "type": "color"
      }
    },
    "$interactional-secondary-03": {
      "$interactional-secondary-03": {
        "value": "#f3f8fb",
        "type": "color"
      },
      "$hover-interactional-secondary-03": {
        "value": "#e8eff3",
        "type": "color"
      },
      "$active-interactional-secondary-03": {
        "1": {
          "value": "#008cff",
          "type": "color"
        },
        "value": "#c3d1d9",
        "type": "color"
      }
    },
    "$interactional-secondary-04": {
      "$interactional-secondary-04": {
        "value": "#00000000",
        "type": "color"
      },
      "$hover-interactional-secondary-04": {
        "value": "#0000004d",
        "type": "color"
      },
      "$active-interactional-secondary-04": {
        "value": "#00000099",
        "type": "color"
      }
    },
    "$interactional-secondary-05": {
      "$interactional-secondary-05": {
        "value": "#defce200",
        "type": "color"
      },
      "$hover-interactional-secondary-05": {
        "value": "#defce2",
        "type": "color"
      },
      "$active-interactional-secondary-05": {
        "value": "#baf5c1",
        "type": "color"
      }
    },
    "$interactional-secondary-06": {
      "$interactional-secondary-06": {
        "value": "#fee5d800",
        "type": "color"
      },
      "$hover-interactional-secondary-06": {
        "value": "#fee5d8",
        "type": "color"
      },
      "$active-interactional-secondary-06": {
        "value": "#fdc5b2",
        "type": "color"
      }
    },
    "$interactional-secondary-07": {
      "$interactional-secondary-07": {
        "value": "#e4f4f900",
        "type": "color"
      },
      "$hover-interactional-secondary-07": {
        "value": "#e4f1f9",
        "type": "color"
      },
      "$active-interactional-secondary-07": {
        "value": "#d1ebfc",
        "type": "color"
      }
    },
    "$interactional-secondary-08": {
      "$interactional-secondary-08": {
        "value": "#e8eff3",
        "type": "color"
      },
      "$hover-interactional-secondary-08": {
        "value": "#dde8ed",
        "type": "color"
      },
      "$active-interactional-secondary-08": {
        "value": "#c3d1d9",
        "type": "color"
      }
    },
    "$interactional-tertiary-01": {
      "$interactional-tertiary-01": {
        "value": "#e8f0f3",
        "type": "color"
      },
      "$hover-interactional-tertiary-01": {
        "value": "#007ee6",
        "type": "color"
      },
      "$active-interactional-tertiary-01": {
        "1": {
          "value": "#008cff",
          "type": "color"
        },
        "value": "#0077d9",
        "type": "color"
      }
    },
    "$interactional-tertiary-02": {
      "$interactional-tertiary-02": {
        "value": "#b4c9d7",
        "type": "color"
      },
      "$hover-interactional-tertiary-02": {
        "value": "#8ca9bd",
        "type": "color"
      },
      "$active-interactional-tertiary-02": {
        "value": "#567a98",
        "type": "color"
      }
    },
    "$interactional-tertiary-03": {
      "$interactional-tertiary-03": {
        "value": "#ffffff",
        "type": "color"
      },
      "$hover-interactional-tertiary-03": {
        "value": "#f3f8fb",
        "type": "color"
      },
      "$active-interactional-tertiary-03": {
        "1": {
          "value": "#008cff",
          "type": "color"
        },
        "value": "#e8eff3",
        "type": "color"
      }
    }
  },
  "Text": {
    "$disabled-text": {
      "value": "#c7cad1",
      "type": "color"
    },
    "$text-02": {
      "value": "#ffffff",
      "type": "color",
      "description": "white"
    },
    "$text-05": {
      "value": "#f7f9fa",
      "type": "color"
    },
    "$text-supprotive-01": {
      "value": "#ffffffa3",
      "type": "color"
    },
    "$text-suppportive-02": {
      "value": "#008cff",
      "type": "color"
    },
    "$text-01": {
      "$text-01": {
        "value": "#172c55",
        "type": "color"
      },
      "$hover-text-01": {
        "1": {
          "value": "#567a98",
          "type": "color"
        },
        "value": "#008cff",
        "type": "color"
      },
      "$active-text-01": {
        "1": {
          "value": "#567a98",
          "type": "color"
        },
        "value": "#008cff",
        "type": "color"
      }
    },
    "$text-03": {
      "$text-03": {
        "value": "#829db4",
        "type": "color"
      },
      "$hover-text-03": {
        "value": "#567a98",
        "type": "color"
      },
      "$active-text-03": {
        "value": "#008cff",
        "type": "color"
      }
    },
    "$text-04": {
      "$text-04": {
        "value": "#567a98",
        "type": "color"
      },
      "$hover-text-04": {
        "value": "#007ee6",
        "type": "color"
      },
      "$active-text-04": {
        "value": "#008cff",
        "type": "color"
      }
    },
    "$text-06": {
      "$text-06": {
        "value": "#ed3e3e",
        "type": "color"
      },
      "$hover-text-06": {
        "value": "#cb2d3b",
        "type": "color"
      },
      "$active-text-06": {
        "value": "#cb2d3b",
        "type": "color"
      }
    },
    "$text-07": {
      "$text-07": {
        "value": "#00a958",
        "type": "color"
      },
      "$hover-text-07": {
        "value": "#218354",
        "type": "color"
      },
      "$active-text-07": {
        "value": "#196541",
        "type": "color"
      }
    }
  },
  "Icons": {
    "$disabled-icon": {
      "value": "#d9dbdf",
      "type": "color"
    },
    "$icon-02": {
      "value": "#ffffff",
      "type": "color",
      "description": "white"
    },
    "$icon-05": {
      "value": "#f7f9fa",
      "type": "color"
    },
    "$icon-supportive-01": {
      "value": "#ffffffa3",
      "type": "color"
    },
    "$icon-01": {
      "$icon-01": {
        "value": "#172c55",
        "type": "color"
      },
      "$hover-icon-01": {
        "1": {
          "value": "#008cff",
          "type": "color"
        },
        "value": "#567a98",
        "type": "color"
      },
      "$active-icon-01": {
        "1": {
          "value": "#567a98",
          "type": "color"
        },
        "value": "#008cff",
        "type": "color"
      }
    },
    "$icon-03": {
      "$icon-03": {
        "value": "#829db4",
        "type": "color"
      },
      "$hover-icon-03": {
        "value": "#567a98",
        "type": "color"
      },
      "$active-icon-03": {
        "value": "#172c55",
        "type": "color"
      }
    },
    "$icon-04": {
      "$icon-04": {
        "value": "#567a98",
        "type": "color"
      },
      "$hover-icon-04": {
        "value": "#007ee6",
        "type": "color"
      },
      "$active-icon-04": {
        "1": {
          "value": "#ffffff",
          "type": "color"
        },
        "value": "#008cff",
        "type": "color"
      }
    },
    "$icon-06": {
      "$icon-06": {
        "value": "#ed3e3e",
        "type": "color"
      },
      "$hover-icon-06": {
        "value": "#cb2d3b",
        "type": "color"
      },
      "$active-icon-06": {
        "value": "#cb2d3b",
        "type": "color"
      }
    },
    "$icon-07": {
      "$icon-07": {
        "value": "#00a958",
        "type": "color"
      },
      "$hover-icon-07": {
        "value": "#218354",
        "type": "color"
      },
      "$active-icon-07": {
        "value": "#196541",
        "type": "color"
      }
    },
    "$icon-08": {
      "$icon-08": {
        "value": "#b4c9d7",
        "type": "color"
      },
      "$hover-icon-08": {
        "value": "#829db4",
        "type": "color"
      },
      "$active-icon-08": {
        "value": "#008cff",
        "type": "color"
      }
    }
  }
}
